nv/__init__.py
nv/__main__.py
nv/exceptions.py
nv/logger.py
nv/msgs.py
nv/node.py
nv/utils.py
nv_framework-1.25.0.dist-info/COPYING
nv_framework-1.25.0.dist-info/METADATA
nv_framework-1.25.0.dist-info/WHEEL
nv_framework-1.25.0.dist-info/entry_points.txt
nv_framework-1.25.0.dist-info/top_level.txt
nv_framework-1.25.0.dist-info/RECORD
