Metadata-Version: 2.1
Name: nv-framework
Version: 1.25.0
Summary: A Python-based robot-focused framework.
Home-page: https://github.com/unmnd
Author: UNMND, Ltd.
Author-email: callum@unmnd.com
License: GPL-3.0-or-later
Requires-Python: >=3.8
License-File: COPYING
Requires-Dist: pyyaml (==6.0)
Requires-Dist: click (==8.0.3)
Requires-Dist: redis (==3.5.3)
Requires-Dist: orjson (==3.6.8)
Requires-Dist: psutil (==5.9.1)
